biopsykit/__init__.py
biopsykit/example_data.py
biopsykit/classification/__init__.py
biopsykit/classification/utils.py
biopsykit/classification/analysis/__init__.py
biopsykit/classification/analysis/_analysis.py
biopsykit/classification/metrics/__init__.py
biopsykit/classification/metrics/_metrics.py
biopsykit/classification/model_selection/__init__.py
biopsykit/classification/model_selection/nested_cv.py
biopsykit/classification/model_selection/sklearn_pipeline_permuter.py
biopsykit/io/__init__.py
biopsykit/io/biomarker.py
biopsykit/io/biopac.py
biopsykit/io/carwatch_logs.py
biopsykit/io/ecg.py
biopsykit/io/eeg.py
biopsykit/io/io.py
biopsykit/io/nilspod.py
biopsykit/io/psg.py
biopsykit/io/saliva.py
biopsykit/io/sleep.py
biopsykit/io/sleep_analyzer.py
biopsykit/io/tfm.py
biopsykit/metadata/__init__.py
biopsykit/metadata/metadata.py
biopsykit/plotting/__init__.py
biopsykit/plotting/plotting.py
biopsykit/protocols/__init__.py
biopsykit/protocols/_utils.py
biopsykit/protocols/base.py
biopsykit/protocols/car.py
biopsykit/protocols/cft.py
biopsykit/protocols/mist.py
biopsykit/protocols/plotting.py
biopsykit/protocols/tsst.py
biopsykit/questionnaires/__init__.py
biopsykit/questionnaires/questionnaires.py
biopsykit/questionnaires/utils.py
biopsykit/saliva/__init__.py
biopsykit/saliva/saliva.py
biopsykit/saliva/utils.py
biopsykit/signals/__init__.py
biopsykit/signals/_base.py
biopsykit/signals/_base_extraction.py
biopsykit/signals/ecg/__init__.py
biopsykit/signals/ecg/_pipeline.py
biopsykit/signals/ecg/ecg.py
biopsykit/signals/ecg/plotting.py
biopsykit/signals/ecg/event_extraction/__init__.py
biopsykit/signals/ecg/event_extraction/_base_ecg_extraction.py
biopsykit/signals/ecg/event_extraction/_q_peak_forounzafar2018.py
biopsykit/signals/ecg/event_extraction/_q_peak_martinez2004_neurokit.py
biopsykit/signals/ecg/event_extraction/_q_peak_scipy_findpeaks_neurokit.py
biopsykit/signals/ecg/event_extraction/_q_peak_vanlien2013.py
biopsykit-0.13.1.dist-info/METADATA
biopsykit-0.13.1.dist-info/WHEEL
biopsykit-0.13.1.dist-info/licenses/AUTHORS.md
biopsykit-0.13.1.dist-info/licenses/LICENSE
biopsykit-0.13.1.dist-info/RECORD
