Metadata-Version: 2.4
Name: biopsykit
Version: 0.13.1
Summary: A Python package for the analysis of biopsychological data.
Project-URL: Homepage, https://github.com/mad-lab-fau/biopsykit
Project-URL: Repository, https://github.com/mad-lab-fau/biopsykit
Author-email: Robert Richer <robert.richer@fau.de>, Arne Küderle <arne.kuederle@fau.de>, Rebecca Lennartz <rebecca.lennartz@fau.de>, Daniel Krauß <daniel.k.krauss@fau.de>, Victoria Müller <victoria.m.mueller@fau.de>, Martin Ullrich <martin.ullrich@fau.de>, Janis Zenkner <janis.zenkner@fau.de>
License-Expression: MIT
License-File: AUTHORS.md
License-File: LICENSE
Requires-Python: <4.0,>=3.9
Requires-Dist: bioread<4,>=3
Requires-Dist: fau-colors~=1.1
Requires-Dist: joblib<2,>=1
Requires-Dist: matplotlib~=3.9
Requires-Dist: neurokit2<0.2.11,>=0
Requires-Dist: nilspodlib>=4.0.0
Requires-Dist: numpy>=1.26
Requires-Dist: openpyxl<4,>=3
Requires-Dist: pandas<3,>=2
Requires-Dist: pingouin<0.6,>=0.5.2
Requires-Dist: scikit-learn~=1.0
Requires-Dist: scipy<2,>=1
Requires-Dist: seaborn<1,>=0
Requires-Dist: statannotations<0.8,>=0.7.1
Requires-Dist: statsmodels<1,>=0
Requires-Dist: tpcp>=1
Requires-Dist: tqdm<5,>=4
Requires-Dist: ts2vg<2,>=1.2.4
Requires-Dist: xlrd<3,>=2
Requires-Dist: xlsxwriter<2,>=1
Provides-Extra: jupyter
Requires-Dist: ipympl<0.10,>=0.9; extra == 'jupyter'
Requires-Dist: ipython<8,>=7; extra == 'jupyter'
Requires-Dist: ipywidgets<9,>=8; extra == 'jupyter'
Provides-Extra: mne
Requires-Dist: mne<2,>=1.2.1; extra == 'mne'
